RsCmwNrFr1Meas/RsCmwNrFr1Meas.py
RsCmwNrFr1Meas/__init__.py
RsCmwNrFr1Meas/enums.py
RsCmwNrFr1Meas/repcap.py
RsCmwNrFr1Meas/CustomFiles/__init__.py
RsCmwNrFr1Meas/CustomFiles/events.py
RsCmwNrFr1Meas/CustomFiles/reliability.py
RsCmwNrFr1Meas/CustomFiles/utilities.py
RsCmwNrFr1Meas/Implementations/__init__.py
RsCmwNrFr1Meas/Implementations/Configure/__init__.py
RsCmwNrFr1Meas/Implementations/Configure/NrSubMeas/RfSettings.py
RsCmwNrFr1Meas/Implementations/Configure/NrSubMeas/Scenario.py
RsCmwNrFr1Meas/Implementations/Configure/NrSubMeas/__init__.py
RsCmwNrFr1Meas/Implementations/Configure/NrSubMeas/BwConfig/Invoke.py
RsCmwNrFr1Meas/Implementations/Configure/NrSubMeas/BwConfig/__init__.py
RsCmwNrFr1Meas/Implementations/Configure/NrSubMeas/Caggregation/AcSpacing.py
RsCmwNrFr1Meas/Implementations/Configure/NrSubMeas/Caggregation/Cbandwidth.py
RsCmwNrFr1Meas/Implementations/Configure/NrSubMeas/Caggregation/__init__.py
RsCmwNrFr1Meas/Implementations/Configure/NrSubMeas/Caggregation/Frequency/Aggregated.py
RsCmwNrFr1Meas/Implementations/Configure/NrSubMeas/Caggregation/Frequency/__init__.py
RsCmwNrFr1Meas/Implementations/Configure/NrSubMeas/Cc/Cbandwidth.py
RsCmwNrFr1Meas/Implementations/Configure/NrSubMeas/Cc/Frequency.py
RsCmwNrFr1Meas/Implementations/Configure/NrSubMeas/Cc/Nallocations.py
RsCmwNrFr1Meas/Implementations/Configure/NrSubMeas/Cc/NbwParts.py
RsCmwNrFr1Meas/Implementations/Configure/NrSubMeas/Cc/PlcId.py
RsCmwNrFr1Meas/Implementations/Configure/NrSubMeas/Cc/TaPosition.py
RsCmwNrFr1Meas/Implementations/Configure/NrSubMeas/Cc/__init__.py
RsCmwNrFr1Meas/Implementations/Configure/NrSubMeas/Cc/Allocation/__init__.py
RsCmwNrFr1Meas/Implementations/Configure/NrSubMeas/Cc/Allocation/Pusch/Additional.py
RsCmwNrFr1Meas/Implementations/Configure/NrSubMeas/Cc/Allocation/Pusch/Sgeneration.py
RsCmwNrFr1Meas/Implementations/Configure/NrSubMeas/Cc/Allocation/Pusch/__init__.py
RsCmwNrFr1Meas/Implementations/Configure/NrSubMeas/Cc/BwPart/__init__.py
RsCmwNrFr1Meas-3.8.42.dist-info/METADATA
RsCmwNrFr1Meas-3.8.42.dist-info/WHEEL
RsCmwNrFr1Meas-3.8.42.dist-info/top_level.txt
RsCmwNrFr1Meas-3.8.42.dist-info/RECORD
